{"breadcrumb":[{"canonical":"/eptour","categories":[],"fullurl":"/eptour","idpath":"|88|","internalid":"88","isprimaryurl":true,"name":"epTOUR","parenturl":""}],"canonical":"/eptour","categories":[],"_debug_requestTime":12,"description":"<p>A new line of products for <strong><i>advanced to elite players</i></strong>, is the next step forward in youth golf. <a href=\"/eptour-overview\"><b>Learn more</b></a> about epTOUR before your purchase.</p>   <p>You can customize your epTOUR golf bag with embroidery for a small up-charge. Choose logo, personalization, or a combo! </p>","fullurl":"/eptour","idpath":"|88|","internalid":"88","isprimaryurl":true,"name":"epTOUR","pagebannerurl":"/core/media/media.nl?id=3004390&c=6222191&h=dwNfSsBaOmlw6J5EwZcyYA0TpFX_-Wo_O_--HS_vkulvifm3","pagetitle":"epTOUR | U.S. Kids Golf","parenturl":"","urlfragment":"eptour"}